opencode_sdk/__init__.py
opencode_sdk/_base_client.py
opencode_sdk/_client.py
opencode_sdk/_compat.py
opencode_sdk/_constants.py
opencode_sdk/_exceptions.py
opencode_sdk/_files.py
opencode_sdk/_models.py
opencode_sdk/_qs.py
opencode_sdk/_resource.py
opencode_sdk/_response.py
opencode_sdk/_streaming.py
opencode_sdk/_types.py
opencode_sdk/_version.py
opencode_sdk/py.typed
opencode_sdk/_utils/__init__.py
opencode_sdk/_utils/_compat.py
opencode_sdk/_utils/_datetime_parse.py
opencode_sdk/_utils/_id_generator.py
opencode_sdk/_utils/_logs.py
opencode_sdk/_utils/_proxy.py
opencode_sdk/_utils/_reflection.py
opencode_sdk/_utils/_resources_proxy.py
opencode_sdk/_utils/_streams.py
opencode_sdk/_utils/_sync.py
opencode_sdk/_utils/_transform.py
opencode_sdk/_utils/_typing.py
opencode_sdk/_utils/_utils.py
opencode_sdk/lib/.keep
opencode_sdk/resources/__init__.py
opencode_sdk/resources/agent.py
opencode_sdk/resources/artifact.py
opencode_sdk/resources/auth.py
opencode_sdk/resources/client_tool.py
opencode_sdk/resources/command.py
opencode_sdk/resources/config.py
opencode_sdk/resources/event.py
opencode_sdk/resources/file.py
opencode_sdk/resources/find.py
opencode_sdk/resources/formatter.py
opencode_sdk/resources/global_.py
opencode_sdk/resources/instance.py
opencode_sdk/resources/log.py
opencode_sdk/resources/lsp.py
opencode_sdk/resources/path.py
opencode_sdk/resources/permission.py
opencode_sdk/resources/project.py
opencode_sdk/resources/pty.py
opencode_sdk/resources/question.py
opencode_sdk/resources/skill.py
opencode_sdk/resources/vcs.py
opencode_sdk/resources/experimental/__init__.py
opencode_sdk/resources/experimental/experimental.py
opencode_sdk/resources/experimental/tool.py
opencode_sdk/resources/experimental/worktree.py
opencode_sdk/resources/mcp/__init__.py
opencode_sdk/resources/mcp/auth.py
opencode_sdk/resources/mcp/mcp.py
opencode_sdk/resources/provider/__init__.py
opencode_sdk/resources/provider/custom.py
opencode_sdk/resources/provider/oauth.py
ai4pa_opencode_sdk-0.11.0.dist-info/METADATA
ai4pa_opencode_sdk-0.11.0.dist-info/WHEEL
ai4pa_opencode_sdk-0.11.0.dist-info/licenses/LICENSE
ai4pa_opencode_sdk-0.11.0.dist-info/RECORD
